{
  "style": "black_white_manga",
  "layout": "3x3",
  "entities": [
    {
      "entity_id": "boy",
      "description": "teenage boy with slim build, wearing a blue hooded raincoat, dark shorts, sneakers, wet bangs visible under hood"
    },
    {
      "entity_id": "cat",
      "description": "small gray cat with short fur, bright eyes, striped tail, sharp ears, expressive face"
    },
    {
      "entity_id": "streetlamp",
      "description": "old metal streetlamp glowing in the rainy night, casting a circular pool of light"
    },
    {
      "entity_id": "alley",
      "description": "narrow city alley at night with wet pavement, brick walls, puddles, distant signs, heavy rain"
    }
  ],
  "panels": [
    {
      "panel_id": 1,
      "summary": "Wide establishing shot of a narrow rainy city alley at night, wet pavement shining under an old streetlamp, dramatic manga rain lines.",
      "entities_used": [
        "alley",
        "streetlamp"
      ],
      "text": [
        {
          "type": "caption",
          "speaker": null,
          "content": "雨夜，巷子深处。",
          "position": "top_left"
        },
        {
          "type": "sfx",
          "speaker": null,
          "content": "哗啦啦",
          "position": "top_right"
        }
      ]
    },
    {
      "panel_id": 2,
      "summary": "The boy in a blue hooded raincoat walks alone through the alley, shoulders hunched against the rain, puddles splashing around his sneakers.",
      "entities_used": [
        "boy",
        "alley"
      ],
      "text": [
        {
          "type": "thought",
          "speaker": "boy",
          "content": "今晚真冷……",
          "position": "top_left"
        }
      ]
    },
    {
      "panel_id": 3,
      "summary": "Low angle close-up of a small gray cat sitting beneath the streetlamp, dry only in the tiny circle of light, staring directly at the boy.",
      "entities_used": [
        "cat",
        "streetlamp",
        "alley"
      ],
      "text": [
        {
          "type": "sfx",
          "speaker": null,
          "content": "喵",
          "position": "bottom_center"
        }
      ]
    },
    {
      "panel_id": 4,
      "summary": "The boy stops suddenly, turning toward the cat with wide eyes; rain drips from his hood, the alley behind him dark and empty.",
      "entities_used": [
        "boy",
        "cat",
        "alley"
      ],
      "text": [
        {
          "type": "speech",
          "speaker": "boy",
          "content": "你迷路了吗？",
          "position": "middle_right"
        }
      ]
    },
    {
      "panel_id": 5,
      "summary": "Close-up on the gray cat lifting its head and speaking calmly, its eyes bright and intelligent; rain streaks frame the panel.",
      "entities_used": [
        "cat"
      ],
      "text": [
        {
          "type": "speech",
          "speaker": "cat",
          "content": "不是。我在等你。",
          "position": "top_center"
        }
      ]
    },
    {
      "panel_id": 6,
      "summary": "The boy recoils in shock, one foot splashing backward into a puddle; the cat remains composed beneath the streetlamp.",
      "entities_used": [
        "boy",
        "cat",
        "streetlamp",
        "alley"
      ],
      "text": [
        {
          "type": "speech",
          "speaker": "boy",
          "content": "猫、猫说话了？！",
          "position": "top_left"
        },
        {
          "type": "sfx",
          "speaker": null,
          "content": "啪嗒",
          "position": "bottom_left"
        }
      ]
    },
    {
      "panel_id": 7,
      "summary": "The cat walks ahead along the wet alley with tail raised, glancing back; the boy hesitantly follows, keeping his hood low.",
      "entities_used": [
        "boy",
        "cat",
        "alley"
      ],
      "text": [
        {
          "type": "speech",
          "speaker": "cat",
          "content": "跟我来。别出声。",
          "position": "top_right"
        }
      ]
    },
    {
      "panel_id": 8,
      "summary": "They reach a darker bend in the alley; the cat paws at a glowing crack between old bricks while the boy kneels beside it, amazed.",
      "entities_used": [
        "boy",
        "cat",
        "alley"
      ],
      "text": [
        {
          "type": "speech",
          "speaker": "boy",
          "content": "这是什么光？",
          "position": "top_left"
        },
        {
          "type": "speech",
          "speaker": "cat",
          "content": "雨夜的门。",
          "position": "bottom_right"
        }
      ]
    },
    {
      "panel_id": 9,
      "summary": "Final dramatic shot: the brick wall opens into a bright mysterious doorway, rain frozen in shimmering lines as the boy and gray cat face it together.",
      "entities_used": [
        "boy",
        "cat",
        "alley"
      ],
      "text": [
        {
          "type": "caption",
          "speaker": null,
          "content": "他们的秘密冒险开始了。",
          "position": "top_center"
        }
      ]
    }
  ]
}